cacheobj/backend
cacheobj/simple
cacheobj
