Metadata-Version: 1.0
Name: cacheobj
Version: 0.9
Summary: A cache interface with python object-property interface.
Home-page: https://github.com/youknowone/cacheobj
Author: Jeong YunWon
Author-email: jeong+cacheobj@youknowone.org
License: UNKNOWN
Platform: UNKNOWN
